ode/__init__.py
ode/authentication_exception.py
ode/base_controller.py
ode/base_view_model.py
ode/callback_decorator.py
ode/chained_use_case.py
ode/composite_job_disposable.py
ode/controller.py
ode/dispatcher_decorator.py
ode/error_output.py
ode/guard_exception.py
ode/http_exception.py
ode/internet_connection_exception.py
ode/output.py
ode/sequence_use_case.py
ode/use_case.py
ode/use_case_decorator.py
ode/use_case_unit.py
ode/value_out_put.py
python_ode-0.0.3.dist-info/METADATA
python_ode-0.0.3.dist-info/WHEEL
python_ode-0.0.3.dist-info/top_level.txt
python_ode-0.0.3.dist-info/RECORD
