Metadata-Version: 2.1
Name: python-ode
Version: 0.0.3
Summary: A framework to drive a clean code
Author: v2SoftwareHouse
